{
    "along_y":{
        "windward_0.5": {
            "case_a": 1.2,
            "case_b": -1.1
        }, 
        "windward_0.5_L": {
            "case_a": 0.3,
            "case_b": -0.1
        },
        "parapets": {
            "windward": 1.5,
            "leeward": -1.0
        }
    },
    "along_x":{
        "windward_h": {
            "case_a": -0.8,
            "case_b": 0.8
        }, 
        "windward_h_2h": {
            "case_a": -0.6,
            "case_b": 0.5
        },
        "windward_2h": {
            "case_a": -0.3,
            "case_b": 0.3
        },
        "parapets": {
            "windward": 1.5,
            "leeward": -1.0
        }
    }
    
}